{
  "id": "00000000-0000-0000-0000-000000000000",
  "prevId": "",
  "version": "7",
  "dialect": "postgresql",
  "tables": {},
  "enums": {
    "public.size": {
      "name": "size",
      "values": [
        "5",
        "10",
        "15",
        "30",
        "50",
        "75",
        "100",
        "125",
        "150",
        "200"
      ],
      "schema": "public"
    },
    "public.status": {
      "name": "status",
      "values": [
        "fulfilled",
        "shipped",
        "awaiting_shipment"
      ],
      "schema": "public"
    }
  },
  "schemas": {},
  "sequences": {},
  "_meta": {
    "schemas": {},
    "tables": {},
    "columns": {}
  },
  "internal": {
    "tables": {}
  }
}